divide/__init__.py
divide/divide_by_three.py
multiply/__init__.py
multiply/multiply_by_three.py
ashpkg-1.0.0.dist-info/LICENSE.txt
ashpkg-1.0.0.dist-info/METADATA
ashpkg-1.0.0.dist-info/WHEEL
ashpkg-1.0.0.dist-info/top_level.txt
ashpkg-1.0.0.dist-info/RECORD
